oslo_concurrency/__init__.py
oslo_concurrency/_i18n.py
oslo_concurrency/lockutils.py
oslo_concurrency/opts.py
oslo_concurrency/prlimit.py
oslo_concurrency/processutils.py
oslo_concurrency/py.typed
oslo_concurrency/version.py
oslo_concurrency/watchdog.py
oslo_concurrency/fixture/__init__.py
oslo_concurrency/fixture/lockutils.py
oslo_concurrency/locale/de/LC_MESSAGES/oslo_concurrency.po
oslo_concurrency/locale/en_GB/LC_MESSAGES/oslo_concurrency.po
oslo_concurrency/locale/es/LC_MESSAGES/oslo_concurrency.po
oslo_concurrency/locale/fr/LC_MESSAGES/oslo_concurrency.po
oslo_concurrency/tests/__init__.py
oslo_concurrency/tests/unit/__init__.py
oslo_concurrency/tests/unit/test_lockutils.py
oslo_concurrency/tests/unit/test_lockutils_eventlet.py
oslo_concurrency/tests/unit/test_processutils.py
oslo_concurrency-7.3.0.dist-info/licenses/AUTHORS
oslo_concurrency-7.3.0.dist-info/licenses/LICENSE
oslo_concurrency-7.3.0.dist-info/METADATA
oslo_concurrency-7.3.0.dist-info/WHEEL
oslo_concurrency-7.3.0.dist-info/entry_points.txt
oslo_concurrency-7.3.0.dist-info/pbr.json
oslo_concurrency-7.3.0.dist-info/top_level.txt
oslo_concurrency-7.3.0.dist-info/RECORD
